iquaflow/__init__.py
iquaflow/_version.py
iquaflow/aws_utils.py
iquaflow/ds_stats.py
iquaflow/sanity.py
iquaflow/version.py
iquaflow/datasets/__init__.py
iquaflow/datasets/ds_exceptions.py
iquaflow/datasets/ds_tools.py
iquaflow/datasets/modifier_blur.py
iquaflow/datasets/modifier_gsd.py
iquaflow/datasets/modifier_jpg.py
iquaflow/datasets/modifier_quant.py
iquaflow/datasets/modifier_rer.py
iquaflow/datasets/modifier_sharpness.py
iquaflow/datasets/modifier_snr.py
iquaflow/datasets/modifier_sr.py
iquaflow/datasets/dataset_labels/RER/DeepGlobe_RER.json
iquaflow/datasets/dataset_labels/RER/inria-aid_RER.json
iquaflow/datasets/dataset_labels/RER/xview_RER.json
iquaflow/datasets/dataset_labels/SNR/DeepGlobe_SNR.json
iquaflow/datasets/dataset_labels/SNR/inria-aid_SNR.json
iquaflow/datasets/dataset_labels/SNR/xview_SNR.json
iquaflow/experiments/__init__.py
iquaflow/experiments/experiment_info.py
iquaflow/experiments/experiment_setup.py
iquaflow/experiments/experiment_visual.py
iquaflow/experiments/task_execution.py
iquaflow/experiments/utils.py
iquaflow/metrics/__init__.py
iquaflow/metrics/base_metric.py
iquaflow/metrics/detection_metrics.py
iquaflow/metrics/rer_metric.py
iquaflow/metrics/sharpness_metric.py
iquaflow/metrics/snr_metric.py
iquaflow/quality_metrics/__init__.py
iquaflow/quality_metrics/benchmark.py
iquaflow/quality_metrics/cfg_generator.py
iquaflow/quality_metrics/dataloader.py
iquaflow/quality_metrics/gaussian_blur_metrics.py
iquaflow/quality_metrics/gsd_metrics.py
iquaflow/quality_metrics/iqf_use_case_metrics.py
iquaflow/quality_metrics/iqf_use_case_sr.py
iquaflow/quality_metrics/loss_regressor.py
iquaflow/quality_metrics/noise_sharpness_metrics.py
iquaflow/quality_metrics/notifier.py
iquaflow/quality_metrics/quality_metrics.py
iquaflow/quality_metrics/regressor.py
iquaflow/quality_metrics/rer_metrics.py
iquaflow/quality_metrics/score_metrics.py
iquaflow/quality_metrics/snr_metrics.py
iquaflow/quality_metrics/tools.py
iquaflow-1.0.1.dist-info/LICENSE
iquaflow-1.0.1.dist-info/METADATA
iquaflow-1.0.1.dist-info/WHEEL
iquaflow-1.0.1.dist-info/top_level.txt
iquaflow-1.0.1.dist-info/RECORD
