Metadata-Version: 2.1
Name: iquaflow
Version: 1.0.1
Summary: Image quality framework
Home-page: https://github.com/satellogic/iquaflow/
Author: Pau Gallés, Katalin Takáts, Emilio Tylson, David Berga, Miguel Hernández-Cabronero, Luciano Pega, Laura Riordan-Chen, Clara Garcia, Guillermo Becker, David Vilaseca, Javier Marín
Maintainer-email: iquaflow@satellogic.com
License: MIT
Download-URL: https://github.com/satellogic/iquaflow/tags/v1.0.1
Platform: UNKNOWN
Requires-Python: >=3.6
License-File: LICENSE
Requires-Dist: numpy (>=1.17)
Requires-Dist: pandas (>=0.22.0)
Requires-Dist: SciPy (>=0.13.3)
Requires-Dist: scikit-learn (>=0.19.1)
Requires-Dist: matplotlib (>=2.2.2)
Requires-Dist: mlflow (>=1.0)
Requires-Dist: GpyOpt (>=1.2.5)
Requires-Dist: geopandas (>=0.8.1)
Requires-Dist: pycocotools (>=2.0.2)
Requires-Dist: opencv-python (==4.4.0.44)
Requires-Dist: easyimages (>=1.91)
Requires-Dist: ipython
Requires-Dist: seaborn (==0.11.1)
Requires-Dist: scikit-image (>=0.17.2)
Requires-Dist: joblib (>=1.0.1)
Requires-Dist: sagemaker (>=2.59.1.post0)
Requires-Dist: boto3
Requires-Dist: torch (>=1.7.1)
Requires-Dist: torchvision (>=0.8.1)
Requires-Dist: rasterio (>=1.2.10)
Requires-Dist: geojson (>=2.5.0)
Provides-Extra: dev
Requires-Dist: pytest ; extra == 'dev'
Requires-Dist: pytest-cov ; extra == 'dev'
Requires-Dist: pytest-mypy ; extra == 'dev'
Requires-Dist: pytest-doctestplus ; extra == 'dev'
Provides-Extra: doc
Requires-Dist: sphinx ; extra == 'doc'
Requires-Dist: sphinx-hoverxref ; extra == 'doc'
